aiida_scheduler/__init__.py
aiida_scheduler/client.py
aiida_scheduler/control.py
aiida_scheduler/scheduler.py
aiida_scheduler/utils.py
aiida_scheduler/backend/__init__.py
aiida_scheduler/backend/scheduler.py
aiida_scheduler/backend/static/scheduler.esm.css
aiida_scheduler/backend/static/scheduler.esm.js
aiida_scheduler/cli/__init__.py
aiida_scheduler/cli/cmd_aiida_scheduler.py
aiida_scheduler/cli/cmd_scheduler.py
aiida_scheduler/orm/scheduler.py
aiida_scheduler/tools/__init__.py
aiida_scheduler/tools/pytest_fixtures/__init__.py
aiida_scheduler/tools/pytest_fixtures/scheduler.py
aiida_scheduler-0.1.2.dist-info/METADATA
aiida_scheduler-0.1.2.dist-info/WHEEL
aiida_scheduler-0.1.2.dist-info/entry_points.txt
aiida_scheduler-0.1.2.dist-info/top_level.txt
aiida_scheduler-0.1.2.dist-info/RECORD
