Metadata-Version: 2.4
Name: aiida_scheduler
Version: 0.1.2
Summary: Process scheduler for AiiDA.
Author-email: Xing Wang <xingwang1991@gmail.com>
Project-URL: Documentation, https://aiida-scheduler.readthedocs.io
Project-URL: Source, https://github.com/aiidateam/aiida-scheduler
Classifier: Development Status :: 1 - Planning
Classifier: Framework :: AiiDA
Classifier: License :: OSI Approved :: MIT License
Classifier: Operating System :: POSIX :: Linux
Classifier: Operating System :: MacOS :: MacOS X
Classifier: Programming Language :: Python
Classifier: Programming Language :: Python :: 3.9
Classifier: Programming Language :: Python :: 3.10
Classifier: Programming Language :: Python :: 3.11
Classifier: Programming Language :: Python :: 3.12
Classifier: Topic :: Scientific/Engineering
Requires-Dist: aiida-scheduler
Provides-Extra: pre-commit
Requires-Dist: pre-commit~=2.2; extra == "pre-commit"
Requires-Dist: pylint~=2.17.4; extra == "pre-commit"
